README.rst
setup.cfg
setup.py
makesurface/__init__.py
makesurface.egg-info/PKG-INFO
makesurface.egg-info/SOURCES.txt
makesurface.egg-info/dependency_links.txt
makesurface.egg-info/entry_points.txt
makesurface.egg-info/not-zip-safe
makesurface.egg-info/requires.txt
makesurface.egg-info/top_level.txt
makesurface/scripts/__init__.py
makesurface/scripts/cli.py
makesurface/scripts/fill_facets.py
makesurface/scripts/tools.py
makesurface/scripts/triangulate_raster.py
makesurface/scripts/vectorize_raster.py