Metadata-Version: 1.0
Name: makesurface
Version: 0.2.12dev
Summary: Create vector datasets from raster surfaces
Home-page: https://github.com/mapbox/make-surface
Author: Damon Burgett
Author-email: damon@mapbox.com
License: MIT
Platform: UNKNOWN
